setup.py
hirschman/__init__.py
hirschman/hirschman.py
hirschman.egg-info/PKG-INFO
hirschman.egg-info/SOURCES.txt
hirschman.egg-info/dependency_links.txt
hirschman.egg-info/requires.txt
hirschman.egg-info/top_level.txt