Metadata-Version: 1.0
Name: hirschman
Version: 1.0.3
Summary: hirschman related computations
Home-page: https://github.com/aes3219563/Hirschman-Transform-Lib
Author: Peng Xi
Author-email: px11@my.fsu.edu
License: MIT Licence
Keywords: pip,hirschman,computations
Platform: any
